series_renamer/__init__.py
series_renamer/__init__.pyc
series_renamer/logs.html
series_renamer/series_renamer.py
series_renamer/series_renamer.pyc
series_renamer-1.1.2.dist-info/DESCRIPTION.rst
series_renamer-1.1.2.dist-info/METADATA
series_renamer-1.1.2.dist-info/RECORD
series_renamer-1.1.2.dist-info/WHEEL
series_renamer-1.1.2.dist-info/entry_points.txt
series_renamer-1.1.2.dist-info/metadata.json
series_renamer-1.1.2.dist-info/top_level.txt
