Metadata-Version: 2.0
Name: series-renamer
Version: 1.1.2
Summary: Robust TV Series Renamer
Home-page: http://github.com/aviaryan/series-renamer
Author: Avi Aryan
Author-email: avi.aryan123@gmail.com
License: UNKNOWN
Keywords: series tv-series tvdb renamer
Platform: UNKNOWN
Classifier: Development Status :: 5 - Production/Stable
Classifier: Topic :: Utilities
Classifier: License :: OSI Approved :: Apache Software License
Classifier: Programming Language :: Python :: 3
Classifier: Programming Language :: Python :: 2
Requires-Dist: tvdb-api
